qt4a/__init__.py
qt4a/__main__.py
qt4a/andrcontrols.py
qt4a/androidapp.py
qt4a/androidtestbase.py
qt4a/browser.py
qt4a/device.py
qt4a/management.py
qt4a/mtcontrols.py
qt4a/qpath.py
qt4a/systemui.py
qt4a/androiddriver/__init__.py
qt4a/androiddriver/_axmlparser.py
qt4a/androiddriver/adb.py
qt4a/androiddriver/adbclient.py
qt4a/androiddriver/androiddriver.py
qt4a/androiddriver/clientsocket.py
qt4a/androiddriver/devicedriver.py
qt4a/androiddriver/util.py
qt4a/androiddriver/webdriver.py
qt4a/androiddriver/tools/AndroidSpy.jar
qt4a/androiddriver/tools/QT4AHelper.apk
qt4a/androiddriver/tools/SpyHelper.jar
qt4a/androiddriver/tools/SpyHelper.sh
qt4a/androiddriver/tools/androidhook.jar
qt4a/androiddriver/tools/inject
qt4a/androiddriver/tools/inject64
qt4a/androiddriver/tools/version.txt
qt4a/androiddriver/tools/adb/darwin/adb
qt4a/androiddriver/tools/adb/linux2/adb
qt4a/androiddriver/tools/adb/win32/AdbWinApi.dll
qt4a/androiddriver/tools/adb/win32/AdbWinUsbApi.dll
qt4a/androiddriver/tools/adb/win32/adb.exe
qt4a/androiddriver/tools/arm64-v8a/droid_inject
qt4a/androiddriver/tools/arm64-v8a/droid_inject64
qt4a/androiddriver/tools/arm64-v8a/libandroidhook.so
qt4a/androiddriver/tools/arm64-v8a/libandroidhook64.so
qt4a/androiddriver/tools/arm64-v8a/libdexloader.so
qt4a/androiddriver/tools/arm64-v8a/libdexloader64.so
qt4a/androiddriver/tools/arm64-v8a/screenkit
qt4a/androiddriver/tools/armeabi/droid_inject
qt4a/androiddriver/tools/armeabi/libdexloader.so
qt4a/androiddriver/tools/armeabi/screenkit
qt4a/androiddriver/tools/armeabi-v7a/droid_inject
qt4a/androiddriver/tools/armeabi-v7a/libandroidhook.so
qt4a/androiddriver/tools/armeabi-v7a/libdexloader.so
qt4a/androiddriver/tools/armeabi-v7a/screenkit
qt4a/androiddriver/tools/x86/droid_inject
qt4a/androiddriver/tools/x86/libandroidhook.so
qt4a/androiddriver/tools/x86/libdexloader.so
qt4a/androiddriver/tools/x86/screenkit
qt4a/androiddriver/tools/x86_64/droid_inject
qt4a/androiddriver/tools/x86_64/droid_inject64
qt4a-3.2.2.dist-info/LICENSE.TXT
qt4a-3.2.2.dist-info/METADATA
qt4a-3.2.2.dist-info/WHEEL
qt4a-3.2.2.dist-info/entry_points.txt
qt4a-3.2.2.dist-info/top_level.txt
qt4a-3.2.2.dist-info/RECORD
