Metadata-Version: 2.1
Name: qt4a
Version: 3.2.2
Summary: QTA driver for Android app
Home-page: https://github.com/Tencent/QT4A
Author: Tencent
License: Copyright(c)2010-2018 Tencent All Rights Reserved. 
Project-URL: QT4A Documentation, https://qt4a.readthedocs.io/zh_CN/latest/
Classifier: Programming Language :: Python :: 2.7
Classifier: Operating System :: OS Independent
License-File: LICENSE.TXT
Requires-Dist: qtaf
Requires-Dist: pillow
Requires-Dist: six
Requires-Dist: future
